pyproprop/__init__.py
pyproprop/format_str_case.py
pyproprop/named_iterable.py
pyproprop/options.py
pyproprop/processed_property.py
pyproprop/utils.py
pyproprop-0.4.10.dist-info/METADATA
pyproprop-0.4.10.dist-info/WHEEL
pyproprop-0.4.10.dist-info/top_level.txt
pyproprop-0.4.10.dist-info/RECORD
