Metadata-Version: 2.1
Name: pyproprop
Version: 0.4.10
Summary: Package for aiding writing classes with lots of similar simple properties without the boilerplate
Home-page: https://pyproprop.readthedocs.io
Author: Sam Brockie
Author-email: sambrockie@icloud.com
License: MIT
Project-URL: Documentation, https://pyproprop.readthedocs.io
Project-URL: PyPI, https://pypi.org/project/pyproprop/
Project-URL: conda-forge, https://anaconda.org/conda-forge/pyproprop
Project-URL: Source Code, https://github.com/brocksam/pyproprop
Project-URL: Bug Tracker, https://github.com/brocksam/pyproprop/issues
Platform: UNKNOWN
Classifier: Development Status :: 3 - Alpha
Classifier: Intended Audience :: Developers
Classifier: Programming Language :: Python :: 3
Classifier: Programming Language :: Python :: 3.6
Classifier: Programming Language :: Python :: 3.7
Classifier: Programming Language :: Python :: 3.8
Classifier: Programming Language :: Python :: 3.9
Classifier: License :: OSI Approved :: MIT License
Classifier: Operating System :: OS Independent
Classifier: Natural Language :: English
Classifier: Topic :: Utilities
Requires-Python: >=3.6
Requires-Dist: numpy (>=1.17)
Requires-Dist: sympy (>=1.6)
Requires-Dist: titlecase (>=2.2)
Requires-Dist: typing (>=3.7)
Provides-Extra: docs
Requires-Dist: sphinx (>=3.2) ; extra == 'docs'
Requires-Dist: sphinx-autodoc-typehints (>=1.11) ; extra == 'docs'
Requires-Dist: sphinx-rtd-theme (>=0.5) ; extra == 'docs'
Provides-Extra: tests
Requires-Dist: codecov (>=2.1) ; extra == 'tests'
Requires-Dist: hypothesis (>=5.26) ; extra == 'tests'
Requires-Dist: pytest (>=6.0) ; extra == 'tests'
